sme_contrib/__init__.py
sme_contrib/optimize.py
sme_contrib/plot.py
sme_contrib-0.0.16.dist-info/LICENSE
sme_contrib-0.0.16.dist-info/METADATA
sme_contrib-0.0.16.dist-info/WHEEL
sme_contrib-0.0.16.dist-info/top_level.txt
sme_contrib-0.0.16.dist-info/RECORD
