Metadata-Version: 2.1
Name: sme-contrib
Version: 0.0.16
Summary: Useful modules for use with sme (Spatial Model Editor)
Author-email: Liam Keegan <liam@keegan.ch>
License: MIT
Project-URL: Homepage, https://spatial-model-editor.github.io/
Project-URL: Documentation, https://sme-contrib.readthedocs.io/
Project-URL: Github, https://github.com/spatial-model-editor/sme-contrib
Project-URL: Issues, https://github.com/spatial-model-editor/sme-contrib/issues
Classifier: Topic :: Scientific/Engineering :: Bio-Informatics
Classifier: License :: OSI Approved :: MIT License
Classifier: Intended Audience :: Science/Research
Classifier: Intended Audience :: Education
Classifier: Natural Language :: English
Classifier: Operating System :: MacOS :: MacOS X
Classifier: Operating System :: Microsoft :: Windows
Classifier: Operating System :: POSIX :: Linux
Classifier: Programming Language :: Python :: 3 :: Only
Classifier: Programming Language :: Python :: 3.7
Classifier: Programming Language :: Python :: 3.8
Classifier: Programming Language :: Python :: 3.9
Classifier: Programming Language :: Python :: 3.10
Classifier: Programming Language :: Python :: 3.11
Requires-Python: >=3.7
License-File: LICENSE
Requires-Dist: matplotlib
Requires-Dist: numpy
Requires-Dist: pillow
Requires-Dist: pyswarms
Requires-Dist: sme >=1.4.0
Provides-Extra: docs
Requires-Dist: ipykernel ; extra == 'docs'
Requires-Dist: matplotlib ; extra == 'docs'
Requires-Dist: nbsphinx ; extra == 'docs'
Requires-Dist: pandoc ; extra == 'docs'
Requires-Dist: sphinx >=4.5.0 ; extra == 'docs'
Requires-Dist: sphinx-rtd-theme >=1.0.0 ; extra == 'docs'
Provides-Extra: tests
Requires-Dist: numdifftools ; extra == 'tests'
Requires-Dist: pytest ; extra == 'tests'
Requires-Dist: pytest-cov ; extra == 'tests'
Requires-Dist: scipy ; extra == 'tests'
